torrent_name_parser/__init__.py
torrent_name_parser/models.py
torrent_name_parser/parse.py
torrent_name_parser/patterns.py
torrent_name_parser-0.1.0.dist-info/licenses/LICENSE
torrent_name_parser-0.1.0.dist-info/METADATA
torrent_name_parser-0.1.0.dist-info/WHEEL
torrent_name_parser-0.1.0.dist-info/top_level.txt
torrent_name_parser-0.1.0.dist-info/RECORD
