Metadata-Version: 2.4
Name: torrent-name-parser
Version: 0.1.0
Summary: Extract media information from torrent-like filenames
Author-email: Dragos Pancescu <dragos.pnc@gmail.com>
License: The MIT License (MIT)
Project-URL: Homepage, https://github.com/DragosPancescu/torrent-name-parser
Project-URL: Source, https://github.com/DragosPancescu/torrent-name-parser
Project-URL: Documentation, https://github.com/DragosPancescu/torrent-name-parser#readme
Project-URL: Issues, https://github.com/DragosPancescu/torrent-name-parser/issues
Keywords: parse,parser,torrent,torrents,name,names,proper,rename,movie,movies,tv,show,shows,series,extract,find,quality,group,codec,audio,resolution,title,season,episode,year,information,filename,filenames,file,files,meaningful
Classifier: Development Status :: 3 - Alpha
Classifier: Intended Audience :: Developers
Classifier: License :: OSI Approved :: MIT License
Classifier: Programming Language :: Python :: 3
Classifier: Programming Language :: Python :: 3.9
Classifier: Programming Language :: Python :: 3.10
Classifier: Programming Language :: Python :: 3.11
Classifier: Programming Language :: Python :: 3.12
Classifier: Programming Language :: Python :: 3.13
Classifier: Topic :: Software Development :: Libraries :: Python Modules
Requires-Python: <3.14,>=3.9
License-File: LICENSE
Provides-Extra: dev
Requires-Dist: pytest; extra == "dev"
Requires-Dist: tox; extra == "dev"
Dynamic: license-file
